azfiles/__init__.py
azfiles/__main__.py
azfiles-2021.8.dist-info/METADATA
azfiles-2021.8.dist-info/WHEEL
azfiles-2021.8.dist-info/entry_points.txt
azfiles-2021.8.dist-info/top_level.txt
azfiles-2021.8.dist-info/RECORD
